twalk/__init__.py
twalk/__main__.py
twalk/twalk.py
twalk-1.0.14.dist-info/entry_points.txt
twalk-1.0.14.dist-info/LICENSE
twalk-1.0.14.dist-info/WHEEL
twalk-1.0.14.dist-info/METADATA
twalk-1.0.14.dist-info/RECORD
