Metadata-Version: 2.1
Name: twalk
Version: 1.0.14
Summary: Condense a directory tree into a single txt file or extract it from one
Home-page: https://github.com/Ovsyanka83/twalk
License: MIT
Author: Ovsyanka
Author-email: szmiev2000@gmail.com
Requires-Python: >=3.6,<4.0
Classifier: License :: OSI Approved :: MIT License
Classifier: Programming Language :: Python :: 3
Classifier: Programming Language :: Python :: 3.10
Classifier: Programming Language :: Python :: 3.6
Classifier: Programming Language :: Python :: 3.7
Classifier: Programming Language :: Python :: 3.8
Classifier: Programming Language :: Python :: 3.9
Project-URL: Repository, https://github.com/Ovsyanka83/twalk
